scotthsieh_projen_statemachine/__init__.py
scotthsieh_projen_statemachine/py.typed
scotthsieh_projen_statemachine/_jsii/__init__.py
scotthsieh_projen_statemachine/_jsii/projen-statemachine-example@2.0.779.jsii.tgz
scotthsieh_projen_statemachine-2.0.779.dist-info/LICENSE
scotthsieh_projen_statemachine-2.0.779.dist-info/METADATA
scotthsieh_projen_statemachine-2.0.779.dist-info/WHEEL
scotthsieh_projen_statemachine-2.0.779.dist-info/top_level.txt
scotthsieh_projen_statemachine-2.0.779.dist-info/RECORD
