Metadata-Version: 2.1
Name: scotthsieh_projen_statemachine
Version: 2.0.779
Summary: An example construct for deploying to npm, PyPi, Maven, and Nuget with Amazon API Gateway and AWS Step Functions.
Home-page: https://github.com/HsiehShuJeng/projen-simple.git
Author: Shu-Jeng Hsieh
License: Apache-2.0
Project-URL: Source, https://github.com/HsiehShuJeng/projen-simple.git
Classifier: Intended Audience :: Developers
Classifier: Operating System :: OS Independent
Classifier: Programming Language :: JavaScript
Classifier: Programming Language :: Python :: 3 :: Only
Classifier: Programming Language :: Python :: 3.9
Classifier: Programming Language :: Python :: 3.10
Classifier: Programming Language :: Python :: 3.11
Classifier: Typing :: Typed
Classifier: Development Status :: 5 - Production/Stable
Classifier: License :: OSI Approved
Requires-Python: ~=3.9
License-File: LICENSE
Requires-Dist: aws-cdk-lib<3.0.0,>=2.27.0
Requires-Dist: constructs<11.0.0,>=10.0.5
Requires-Dist: jsii<2.0.0,>=1.112.0
Requires-Dist: publication>=0.0.3
Requires-Dist: typeguard<4.3.0,>=2.13.3
